{
  "accessibility_support": [
    "digital-accessibility-caption-audio",
    "digital-accessibility-text-and-visuals-can-be-resized",
    "digital-accessibility-sufficient-contrast",
    "digital-accessibility-motions-or-animations",
    "digital-accessibility-description-of-visual-information",
    "digital-accessibility-all-content-meets-wcag",
    "non-digital-accessibility-description-of-visual-information"
  ],
  "accessibility_support_other": "",
  "audience": [
    "audience_content_author",
    "audience_designer"
  ],
  "check_correct_info": "on",
  "check_publish_info": "on",
  "check_scope_info": "on",
  "comments": "",
  "content_update": "2022-10-26",
  "cost": "cost_paid",
  "country": [
    "gb"
  ],
  "description": "This course is created to enable designers to both write and design accessible, inclusive content with people with disabilities in mind. It covers how, assistive technologies handle content, content design, inclusive language, and useful tools to use when testing content for accessibility.",
  "end_date": "",
  "form_name": "submission",
  "form_version": "1",
  "format": "format_online",
  "language": [
    "en"
  ],
  "learning": [
    "learning_unscheduled"
  ],
  "length": "3 hours",
  "level": "level_basic",
  "platforms": [
    "HTML",
    "SCORM"
  ],
  "prerequisites": [
    "Basic knowledge of W3C accessibility concepts"
  ],
  "provider": "TetraLogical",
  "repository": "wai-course-list",
  "reviews": "",
  "start_date": "2022-12-16",
  "submission_date": "2022-12-01T10:47:33.468Z",
  "submission_ref": "8fb039c0-7165-11ed-8da1-dd1f74063d85",
  "submitter_email": "fminers-jones@tetralogical.com",
  "submitter_name": "Felicity Miners-Jones",
  "title": "Accessible content design",
  "topics": [
    "How assistive technology handles content",
    "Content design (including structure, links, images and forms)",
    "Writing accessible content",
    "Inclusive language",
    "Testing content for accessibility."
  ],
  "type_registration": [
    "type_registration_organization"
  ],
  "type_resource": "type_training",
  "type_resource_new": "",
  "website": "https://tetralogical.com/services/self-led-training/"
}
